recruitment2/__init__.py
recruitment2/admin.py
recruitment2/apps.py
recruitment2/forms.py
recruitment2/models.py
recruitment2/signals.py
recruitment2/tests.py
recruitment2/urls.py
recruitment2/utils.py
recruitment2/views.py
recruitment2/migrations/0001_initial.py
recruitment2/migrations/0002_reccandidate_user_reccandoral_user_reccandscore_user_and_more.py
recruitment2/migrations/0003_recplan_user.py
recruitment2/migrations/0004_candidate_candoral_candscore_candshortlist_and_more.py
recruitment2/migrations/0005_painel_is_active_painel_user.py
recruitment2/migrations/0006_rename_score_shortlistcat_percent_remove_plan_total_and_more.py
recruitment2/migrations/0007_rename_short_list_cat_candshortlist_category.py
recruitment2/migrations/0008_rename_score_candshortlist_total_and_more.py
recruitment2/migrations/0009_rename_comment_candshortlist_comment_a_and_more.py
recruitment2/migrations/0010_painel_plan_pos.py
recruitment2/migrations/0011_rename_oral_score_candscore_score_a_and_more.py
recruitment2/migrations/0012_remove_candoral_score_remove_candwritten_score_and_more.py
recruitment2/migrations/0013_candidate_is_ready.py
recruitment2/migrations/0014_candidate_sex_alter_candoral_score_a_and_more.py
recruitment2/migrations/0015_candscore_sort.py
recruitment2/migrations/0016_alter_candidate_email.py
recruitment2/migrations/0017_plan_is_active.py
recruitment2/migrations/0018_auto_20221212_2036.py
recruitment2/migrations/0019_auto_20230201_1013.py
recruitment2/migrations/0020_plan_description.py
recruitment2/migrations/0021_alter_planunit_unit.py
recruitment2/migrations/0022_candidatecv_candidateshorlistsum_shortlisttype.py
recruitment2/migrations/0023_planattach.py
recruitment2/migrations/0024_planattach_hashed.py
recruitment2/migrations/0025_auto_20230215_1338.py
recruitment2/migrations/0026_planpos_number.py
recruitment2/migrations/__init__.py
recruitment2/migrations/__pycache__/0001_initial.cpython-310.pyc
recruitment2/migrations/__pycache__/0001_initial.cpython-39.pyc
django_ipghrms_recruitment2-1.0.dist-info/LICENSE
django_ipghrms_recruitment2-1.0.dist-info/METADATA
django_ipghrms_recruitment2-1.0.dist-info/WHEEL
django_ipghrms_recruitment2-1.0.dist-info/top_level.txt
django_ipghrms_recruitment2-1.0.dist-info/RECORD
